{
  "project_info": {
    "project_number": "289069566447",
    "project_id": "calmify-aec44",
    "storage_bucket": "calmify-aec44.appspot.com"
  },
  "client": [
    {
      "client_info": {
        "mobilesdk_app_id": "1:289069566447:android:2bb812b56524457701ce1a",
        "android_client_info": {
          "package_name": "com.example.calmify"
        }
      },
      "oauth_client": [
        {
          "client_id": "289069566447-g9ivuc94115v740mapi5ldpqjk652jav.apps.googleusercontent.com",
          "client_type": 3
        }
      ],
      "api_key": [
        {
          "current_key": "AIzaSyAHEjutcZdRJEZ3h42yJpWcoNglYiKrXK0"
        }
      ],
      "services": {
        "appinvite_service": {
          "other_platform_oauth_client": [
            {
              "client_id": "289069566447-g9ivuc94115v740mapi5ldpqjk652jav.apps.googleusercontent.com",
              "client_type": 3
            }
          ]
        }
      }
    }
  ],
  "configuration_version": "1"
}